nood/__init__.py
nood/api/__init__.py
nood/api/mapper.py
nood/api/responses.py
nood/api/types.py
nood/config.py
nood/monitor/__init__.py
nood/monitor/exceptions.py
nood/monitor/monitor.py
nood/monitor/parser.py
nood/monitor/scraper.py
nood/objects/__init__.py
nood/objects/config.py
nood/objects/product.py
nood/objects/proxy.py
nood-0.1.12.dist-info/WHEEL
nood-0.1.12.dist-info/METADATA
nood-0.1.12.dist-info/RECORD
