Metadata-Version: 2.1
Name: nood
Version: 0.1.12
Summary: All tools you need to interact with nood.
Author: timreibe
Author-email: github@timreibe.de
Requires-Python: >=3.9,<4.0
Classifier: Programming Language :: Python :: 3
Classifier: Programming Language :: Python :: 3.9
Classifier: Programming Language :: Python :: 3.10
Classifier: Programming Language :: Python :: 3.11
Requires-Dist: loguru (>=0.6.0,<0.7.0)
Requires-Dist: pydantic (>=1.10.4,<1.11.0)
Requires-Dist: pytest (>=7.2.0,<7.3.0)
Requires-Dist: requests (>=2.28.1)
